MANIFEST.in
README.rst
setup.py
SEEmpty/__init__.py
SEEmpty/admin.py
SEEmpty/models.py
SEEmpty/tests.py
SEEmpty/urls.py
SEEmpty/views.py
se_django_empty.egg-info/PKG-INFO
se_django_empty.egg-info/SOURCES.txt
se_django_empty.egg-info/dependency_links.txt
se_django_empty.egg-info/requires.txt
se_django_empty.egg-info/top_level.txt