Metadata-Version: 1.1
Name: se-django-empty
Version: 0.1
Summary: An empty test package for testing.
Home-page: http://www.example.com/
Author: Lin Myat
Author-email: soelinmyat@gmail.com
License: BSD License
Platform: UNKNOWN
Classifier: Environment :: Web Environment
Classifier: Framework :: Django
Classifier: Intended Audience :: Developers
Classifier: License :: OSI Approved :: BSD License
Classifier: Operating System :: OS Independent
Classifier: Programming Language :: Python
Classifier: Topic :: Internet :: WWW/HTTP
Classifier: Topic :: Internet :: WWW/HTTP :: Dynamic Content
